icat/__init__.py
icat/__main__.py
icat/imageSelect.py
icat-0.0.39.data/scripts/icat
icat-0.0.39.dist-info/LICENSE
icat-0.0.39.dist-info/METADATA
icat-0.0.39.dist-info/WHEEL
icat-0.0.39.dist-info/top_level.txt
icat-0.0.39.dist-info/RECORD
